{"id":"index.html","dependencies":[{"name":"./main.js","dynamic":true,"parent":"C:\\Users\\Administrator\\Desktop\\dom-2\\src\\index.html","resolved":"C:\\Users\\Administrator\\Desktop\\dom-2\\src\\main.js"},{"name":"./dom.js","dynamic":true,"parent":"C:\\Users\\Administrator\\Desktop\\dom-2\\src\\index.html","resolved":"C:\\Users\\Administrator\\Desktop\\dom-2\\src\\dom.js"}],"generated":{"html":"<!DOCTYPE html>\r\n<html lang=\"zh\">\r\n\r\n<head>\r\n    <meta charset=\"UTF-8\">\r\n    <meta http-equiv=\"X-UA-Compatible\" content=\"IE=edge\">\r\n    <meta name=\"viewport\" content=\"width=device-width, initial-scale=1.0\">\r\n    <title>Document</title>\r\n</head>\r\n\r\n<body>\r\n    示例\r\n    <div id=\"div\">我是div</div>\r\n    <div id=\"test\" style=\"color:red\">\r\n        <div class=\"red\">1</div>\r\n        <div class=\"red\">2</div>\r\n        <div class=\"red\">3</div>\r\n\r\n\r\n        <script src=\"/10d45ac3c090f7134f3131dbae54240f.js\"></script>\r\n        <script src=\"/0e3c5ea8c6d88adba0e9ae9e77a39b31.js\"></script>\r\n</div></body>\r\n\r\n</html>"},"hash":"39954bb0832f78189e66e0de225ed1a6","cacheData":{}}